piston/__init__.py
piston/__main__.py
piston/_custom_click.py
piston/cli.py
piston/commands/__init__.py
piston/commands/file.py
piston/commands/input.py
piston/commands/link.py
piston/commands/shell.py
piston/commands/theme_list.py
piston/configuration/__init__.py
piston/configuration/choose_config.py
piston/configuration/config_fixer.py
piston/configuration/config_loader.py
piston/configuration/validators/__init__.py
piston/configuration/validators/box_validator.py
piston/configuration/validators/prompt_validator.py
piston/configuration/validators/theme_validator.py
piston/configuration/validators/validator_base.py
piston/log.py
piston/utils/__init__.py
piston/utils/compilers.py
piston/utils/constants.py
piston/utils/helpers.py
piston/utils/lang_extensions.py
piston/utils/lexers.py
piston/utils/maketable.py
piston/utils/services.py
piston_cli-1.5.0.dist-info/entry_points.txt
piston_cli-1.5.0.dist-info/LICENSE
piston_cli-1.5.0.dist-info/WHEEL
piston_cli-1.5.0.dist-info/METADATA
piston_cli-1.5.0.dist-info/RECORD
