Metadata-Version: 2.1
Name: piston-cli
Version: 1.5.0
Summary: A cli tool with an terminal editor to compile over 35 languages instantly using the piston api.
Home-page: https://github.com/Shivansh-007/piston-cli
License: MIT
Keywords: shell,cli,code-editor,code-execution,compile,piston
Author: Shivansh-007
Author-email: shivansh-007@outlook.com
Requires-Python: >=3.9,<4.0
Classifier: License :: OSI Approved :: MIT License
Classifier: Programming Language :: Python
Classifier: Programming Language :: Python :: 3
Classifier: Programming Language :: Python :: 3.9
Requires-Dist: PyYAML (>=5.4.1,<6.0.0)
Requires-Dist: appdirs (>=1.4.4,<2.0.0)
Requires-Dist: click (>=8.0.1,<9.0.0)
Requires-Dist: coloredlogs (>=15.0.1,<16.0.0)
Requires-Dist: more-itertools (>=8.7.0,<9.0.0)
Requires-Dist: prompt-toolkit (>=3.0.18,<4.0.0)
Requires-Dist: pygments (>=2.8.1,<3.0.0)
Requires-Dist: requests (>=2.25.1,<3.0.0)
Requires-Dist: requests-cache (>=0.8.1,<0.9.0)
Requires-Dist: rich (>=10.1.0,<11.0.0)
Project-URL: Repository, https://github.com/Shivansh-007/piston-cli
